lingua.libs/libgcc_s-e52197c3.so.1
lingua/__init__.py
lingua/__init__.pyi
lingua/lingua.pypy311-pp73-aarch64-linux-gnu.so
lingua/py.typed
lingua_language_detector-2.1.1.dist-info/METADATA
lingua_language_detector-2.1.1.dist-info/WHEEL
lingua_language_detector-2.1.1.dist-info/licenses/LICENSE
lingua_language_detector-2.1.1.dist-info/RECORD
