Metadata-Version: 2.4
Name: lingua-language-detector
Version: 2.1.1
Classifier: Development Status :: 5 - Production/Stable
Classifier: Intended Audience :: Developers
Classifier: Intended Audience :: Information Technology
Classifier: Intended Audience :: Science/Research
Classifier: License :: OSI Approved :: Apache Software License
Classifier: Natural Language :: Afrikaans
Classifier: Natural Language :: Arabic
Classifier: Natural Language :: Basque
Classifier: Natural Language :: Bengali
Classifier: Natural Language :: Bosnian
Classifier: Natural Language :: Bulgarian
Classifier: Natural Language :: Catalan
Classifier: Natural Language :: Chinese (Simplified)
Classifier: Natural Language :: Chinese (Traditional)
Classifier: Natural Language :: Croatian
Classifier: Natural Language :: Czech
Classifier: Natural Language :: Danish
Classifier: Natural Language :: Dutch
Classifier: Natural Language :: English
Classifier: Natural Language :: Esperanto
Classifier: Natural Language :: Finnish
Classifier: Natural Language :: French
Classifier: Natural Language :: German
Classifier: Natural Language :: Greek
Classifier: Natural Language :: Hebrew
Classifier: Natural Language :: Hindi
Classifier: Natural Language :: Hungarian
Classifier: Natural Language :: Icelandic
Classifier: Natural Language :: Indonesian
Classifier: Natural Language :: Irish
Classifier: Natural Language :: Italian
Classifier: Natural Language :: Japanese
Classifier: Natural Language :: Korean
Classifier: Natural Language :: Latin
Classifier: Natural Language :: Latvian
Classifier: Natural Language :: Lithuanian
Classifier: Natural Language :: Macedonian
Classifier: Natural Language :: Malay
Classifier: Natural Language :: Marathi
Classifier: Natural Language :: Norwegian
Classifier: Natural Language :: Panjabi
Classifier: Natural Language :: Persian
Classifier: Natural Language :: Polish
Classifier: Natural Language :: Portuguese
Classifier: Natural Language :: Romanian
Classifier: Natural Language :: Russian
Classifier: Natural Language :: Serbian
Classifier: Natural Language :: Slovak
Classifier: Natural Language :: Slovenian
Classifier: Natural Language :: Spanish
Classifier: Natural Language :: Swedish
Classifier: Natural Language :: Tamil
Classifier: Natural Language :: Telugu
Classifier: Natural Language :: Thai
Classifier: Natural Language :: Turkish
Classifier: Natural Language :: Ukrainian
Classifier: Natural Language :: Urdu
Classifier: Natural Language :: Vietnamese
Classifier: Operating System :: OS Independent
Classifier: Programming Language :: Python :: 3.10
Classifier: Programming Language :: Python :: 3.11
Classifier: Programming Language :: Python :: 3.12
Classifier: Programming Language :: Python :: 3.13
Classifier: Programming Language :: Rust
Classifier: Topic :: Scientific/Engineering :: Information Analysis
Classifier: Topic :: Software Development :: Libraries :: Python Modules
Classifier: Topic :: Software Development :: Internationalization
Classifier: Topic :: Software Development :: Localization
Classifier: Topic :: Text Processing :: Linguistic
Classifier: Typing :: Typed
Requires-Dist: pytest==8.3.4 ; extra == 'test'
Provides-Extra: test
License-File: LICENSE
Summary: An accurate natural language detection library, suitable for short text and mixed-language text
Keywords: language-processing,language-detection,language-recognition,nlp
Home-Page: https://github.com/pemistahl/lingua-rs
Author: Peter M. Stahl <pemistahl@gmail.com>
Author-email: "Peter M. Stahl" <pemistahl@gmail.com>
License: Apache-2.0
Requires-Python: >=3.10
Project-URL: homepage, https://github.com/pemistahl/lingua-py
Project-URL: repository, https://github.com/pemistahl/lingua-py
